guarani/__init__.py
guarani/adapter.py
guarani/authentication/__init__.py
guarani/authentication/client_authentication.py
guarani/authentication/methods/__init__.py
guarani/authentication/methods/base.py
guarani/authentication/methods/client_secret_basic.py
guarani/authentication/methods/client_secret_post.py
guarani/authentication/methods/none.py
guarani/claims.py
guarani/configuration.py
guarani/endpoints/__init__.py
guarani/endpoints/authorization.py
guarani/endpoints/base.py
guarani/endpoints/revocation.py
guarani/endpoints/token.py
guarani/exceptions.py
guarani/grants/__init__.py
guarani/grants/authorization_code.py
guarani/grants/base.py
guarani/grants/client_credentials.py
guarani/grants/refresh_token.py
guarani/mixins/__init__.py
guarani/mixins/authorization_code.py
guarani/mixins/client.py
guarani/mixins/refresh_token.py
guarani/mixins/user.py
guarani/models/__init__.py
guarani/models/http.py
guarani/models/scopes.py
guarani/providers/__init__.py
guarani/providers/base.py
guarani/providers/starlette.py
guarani/utils.py
guarani-1.0.1.dist-info/LICENSE
guarani-1.0.1.dist-info/WHEEL
guarani-1.0.1.dist-info/METADATA
guarani-1.0.1.dist-info/RECORD
