Metadata-Version: 2.1
Name: guarani
Version: 1.0.1
Summary: Asynchronous Authorization, Authentication and Identity Provider for Python using OAuth 2.1 and OpenID Connect.
Home-page: https://github.com/revensky/guarani
License: MIT
Keywords: JOSE,OAuth 2.1,OpenID Connect
Author: Eduardo Rezende
Author-email: eduardorbr7@gmail.com
Requires-Python: >=3.8,<4.0
Classifier: Development Status :: 4 - Beta
Classifier: Environment :: Web Environment
Classifier: Framework :: AsyncIO
Classifier: Intended Audience :: Developers
Classifier: License :: OSI Approved :: MIT License
Classifier: Operating System :: OS Independent
Classifier: Programming Language :: Python :: 3
Classifier: Programming Language :: Python :: 3.8
Classifier: Programming Language :: Python :: 3.9
Classifier: Topic :: Software Development :: Libraries :: Application Frameworks
Classifier: Typing :: Typed
Requires-Dist: shiro (>=0.2.2,<0.3.0)
Project-URL: Repository, https://github.com/revensky/guarani.git
